<?xml version = '1.0' encoding = 'UTF-8'?>
<TableProxyOraclev12c class="oracle.dbtools.crest.model.design.storage.oracle.v12c.TableProxyOraclev12c" name="PER_PERSON_ANALYSES" directorySegmentName="seg_0" id="583A2D48-CCAF-C80E-B1D4-783752A69D52">
<createdBy>vs52761</createdBy>
<createdTime>2024-05-21 13:56:08 UTC</createdTime>
<ownerDesignName>BORIS-HR</ownerDesignName>
<schemaObject>DF1B45F9-635F-5144-8353-0832859A4CDB</schemaObject>
<logging>YES</logging>
<partitionedRowMovement>DISABLE</partitionedRowMovement>
<segment>C9A8C0AB-179F-4E50-1A2B-4134A82A0F11</segment>
<tableSpace>A259311E-A01D-25F0-FFAD-F7D6D4B0EAC7</tableSpace>
<temporaryChanged>false</temporaryChanged>
<accessDriverType>oracle_loader</accessDriverType>
<rejectLimit></rejectLimit>
<inMemory>NO</inMemory>
<columnProxies itemClass="oracle.dbtools.crest.model.design.storage.oracle.v12c.ColumnProxyOraclev12c">
<ColumnProxy name="BUSINESS_GROUP_ID" id="0479F03C-F126-A2D3-27B0-90C6FBBFC860">
<createdBy>vs52761</createdBy>
<createdTime>2024-05-21 13:56:12 UTC</createdTime>
<ownerDesignName>BORIS-HR</ownerDesignName>
</ColumnProxy>
<ColumnProxy name="ATTRIBUTE_CATEGORY" id="09194128-F800-5EF4-AB09-C9EE8A3AE1E1">
<createdBy>vs52761</createdBy>
<createdTime>2024-05-21 13:56:12 UTC</createdTime>
<ownerDesignName>BORIS-HR</ownerDesignName>
</ColumnProxy>
<ColumnProxy name="ATTRIBUTE19" id="0B825085-E8A6-0A5B-CF65-D9CF8D40F637">
<createdBy>vs52761</createdBy>
<createdTime>2024-05-21 13:56:12 UTC</createdTime>
<ownerDesignName>BORIS-HR</ownerDesignName>
</ColumnProxy>
<ColumnProxy name="CREATED_BY" id="0FD66B85-7F1A-9DAA-B4A9-B88219562959">
<createdBy>vs52761</createdBy>
<createdTime>2024-05-21 13:56:12 UTC</createdTime>
<ownerDesignName>BORIS-HR</ownerDesignName>
</ColumnProxy>
<ColumnProxy name="ATTRIBUTE8" id="116A8208-D72F-8CEC-C90E-6D9A07E362ED">
<createdBy>vs52761</createdBy>
<createdTime>2024-05-21 13:56:12 UTC</createdTime>
<ownerDesignName>BORIS-HR</ownerDesignName>
</ColumnProxy>
<ColumnProxy name="CREATION_DATE" id="12D04AF4-A03B-7AA6-152F-61ED2C5BA1B1">
<createdBy>vs52761</createdBy>
<createdTime>2024-05-21 13:56:12 UTC</createdTime>
<ownerDesignName>BORIS-HR</ownerDesignName>
</ColumnProxy>
<ColumnProxy name="ATTRIBUTE15" id="186C7433-EDD8-6B7D-97B5-8A3B5CCFBC67">
<createdBy>vs52761</createdBy>
<createdTime>2024-05-21 13:56:12 UTC</createdTime>
<ownerDesignName>BORIS-HR</ownerDesignName>
</ColumnProxy>
<ColumnProxy name="COMMENTS" id="1D38832A-C0AB-8C7A-3A62-A8FAF44BF165">
<createdBy>vs52761</createdBy>
<createdTime>2024-05-21 13:56:12 UTC</createdTime>
<ownerDesignName>BORIS-HR</ownerDesignName>
</ColumnProxy>
<ColumnProxy name="ATTRIBUTE13" id="1FB53187-5AEE-C721-555E-E1D027D74208">
<createdBy>vs52761</createdBy>
<createdTime>2024-05-21 13:56:12 UTC</createdTime>
<ownerDesignName>BORIS-HR</ownerDesignName>
</ColumnProxy>
<ColumnProxy name="PROGRAM_UPDATE_DATE" id="21E702FC-4BD3-7C5A-023C-CA9F57B68F58">
<createdBy>vs52761</createdBy>
<createdTime>2024-05-21 13:56:12 UTC</createdTime>
<ownerDesignName>BORIS-HR</ownerDesignName>
</ColumnProxy>
<ColumnProxy name="LAST_UPDATE_DATE" id="25CB81E9-58AB-3948-AC03-10E0BC837630">
<createdBy>vs52761</createdBy>
<createdTime>2024-05-21 13:56:12 UTC</createdTime>
<ownerDesignName>BORIS-HR</ownerDesignName>
</ColumnProxy>
<ColumnProxy name="PROGRAM_ID" id="3A9C82BE-F5AB-386F-D338-95D0A6741F0E">
<createdBy>vs52761</createdBy>
<createdTime>2024-05-21 13:56:12 UTC</createdTime>
<ownerDesignName>BORIS-HR</ownerDesignName>
</ColumnProxy>
<ColumnProxy name="ANALYSIS_CRITERIA_ID" id="47DF0F6B-A631-2C24-FD06-96E562CD665B">
<createdBy>vs52761</createdBy>
<createdTime>2024-05-21 13:56:12 UTC</createdTime>
<ownerDesignName>BORIS-HR</ownerDesignName>
</ColumnProxy>
<ColumnProxy name="ATTRIBUTE12" id="4A901798-9131-6856-91F6-FA157EDB99DB">
<createdBy>vs52761</createdBy>
<createdTime>2024-05-21 13:56:12 UTC</createdTime>
<ownerDesignName>BORIS-HR</ownerDesignName>
</ColumnProxy>
<ColumnProxy name="ATTRIBUTE7" id="4EBBBE0F-A6E8-21EB-0D21-4191E0447705">
<createdBy>vs52761</createdBy>
<createdTime>2024-05-21 13:56:12 UTC</createdTime>
<ownerDesignName>BORIS-HR</ownerDesignName>
</ColumnProxy>
<ColumnProxy name="LAST_UPDATED_BY" id="50C999DA-6FB8-D42B-8CEC-F470DB84130F">
<createdBy>vs52761</createdBy>
<createdTime>2024-05-21 13:56:12 UTC</createdTime>
<ownerDesignName>BORIS-HR</ownerDesignName>
</ColumnProxy>
<ColumnProxy name="ID_FLEX_NUM" id="5364C175-8982-2F18-D826-30F297E5C432">
<createdBy>vs52761</createdBy>
<createdTime>2024-05-21 13:56:12 UTC</createdTime>
<ownerDesignName>BORIS-HR</ownerDesignName>
</ColumnProxy>
<ColumnProxy name="PROGRAM_APPLICATION_ID" id="5BFE4A38-FD0C-F4FE-4B75-855B6D26DD28">
<createdBy>vs52761</createdBy>
<createdTime>2024-05-21 13:56:12 UTC</createdTime>
<ownerDesignName>BORIS-HR</ownerDesignName>
</ColumnProxy>
<ColumnProxy name="PERSON_ANALYSIS_ID" id="5D76888F-52E9-5E30-D276-C870C4F2C419">
<createdBy>vs52761</createdBy>
<createdTime>2024-05-21 13:56:12 UTC</createdTime>
<ownerDesignName>BORIS-HR</ownerDesignName>
</ColumnProxy>
<ColumnProxy name="ATTRIBUTE2" id="60982FAD-6F3A-5CCB-3B25-1CE69D653EBD">
<createdBy>vs52761</createdBy>
<createdTime>2024-05-21 13:56:12 UTC</createdTime>
<ownerDesignName>BORIS-HR</ownerDesignName>
</ColumnProxy>
<ColumnProxy name="ATTRIBUTE16" id="68818019-C012-EFB0-A3DB-AB273F633951">
<createdBy>vs52761</createdBy>
<createdTime>2024-05-21 13:56:12 UTC</createdTime>
<ownerDesignName>BORIS-HR</ownerDesignName>
</ColumnProxy>
<ColumnProxy name="PERSON_ID" id="6DACA6EA-7FDD-9EC2-23D5-2A6FB5AA69E2">
<createdBy>vs52761</createdBy>
<createdTime>2024-05-21 13:56:12 UTC</createdTime>
<ownerDesignName>BORIS-HR</ownerDesignName>
</ColumnProxy>
<ColumnProxy name="OBJECT_VERSION_NUMBER" id="72A4F892-A96C-69CC-363A-121F777C03EA">
<createdBy>vs52761</createdBy>
<createdTime>2024-05-21 13:56:12 UTC</createdTime>
<ownerDesignName>BORIS-HR</ownerDesignName>
</ColumnProxy>
<ColumnProxy name="ATTRIBUTE6" id="78B2A814-BD6F-8792-8345-C882762FA257">
<createdBy>vs52761</createdBy>
<createdTime>2024-05-21 13:56:12 UTC</createdTime>
<ownerDesignName>BORIS-HR</ownerDesignName>
</ColumnProxy>
<ColumnProxy name="ATTRIBUTE20" id="853D3D1A-0F7A-ABAF-5C05-667D93BE4586">
<createdBy>vs52761</createdBy>
<createdTime>2024-05-21 13:56:12 UTC</createdTime>
<ownerDesignName>BORIS-HR</ownerDesignName>
</ColumnProxy>
<ColumnProxy name="ATTRIBUTE5" id="911B75AF-B9C2-DC4C-C7A3-A601A305C8D2">
<createdBy>vs52761</createdBy>
<createdTime>2024-05-21 13:56:12 UTC</createdTime>
<ownerDesignName>BORIS-HR</ownerDesignName>
</ColumnProxy>
<ColumnProxy name="ATTRIBUTE1" id="94CB29BC-DC16-AB51-961E-980D849F8E8B">
<createdBy>vs52761</createdBy>
<createdTime>2024-05-21 13:56:12 UTC</createdTime>
<ownerDesignName>BORIS-HR</ownerDesignName>
</ColumnProxy>
<ColumnProxy name="DATE_TO" id="96103593-BAAD-0D04-F7C0-969A18CB0947">
<createdBy>vs52761</createdBy>
<createdTime>2024-05-21 13:56:12 UTC</createdTime>
<ownerDesignName>BORIS-HR</ownerDesignName>
</ColumnProxy>
<ColumnProxy name="ATTRIBUTE3" id="97ACC25A-17D6-AB43-DCE1-A81145D7E138">
<createdBy>vs52761</createdBy>
<createdTime>2024-05-21 13:56:12 UTC</createdTime>
<ownerDesignName>BORIS-HR</ownerDesignName>
</ColumnProxy>
<ColumnProxy name="ATTRIBUTE10" id="A4D580F4-DF92-193E-960A-72451406FDD3">
<createdBy>vs52761</createdBy>
<createdTime>2024-05-21 13:56:12 UTC</createdTime>
<ownerDesignName>BORIS-HR</ownerDesignName>
</ColumnProxy>
<ColumnProxy name="ATTRIBUTE17" id="AC8313EF-001D-AAF4-3A3D-2B1387BBB03C">
<createdBy>vs52761</createdBy>
<createdTime>2024-05-21 13:56:12 UTC</createdTime>
<ownerDesignName>BORIS-HR</ownerDesignName>
</ColumnProxy>
<ColumnProxy name="PARTY_ID" id="B2021067-B747-B450-02C1-C192B8BCE523">
<createdBy>vs52761</createdBy>
<createdTime>2024-05-21 13:56:12 UTC</createdTime>
<ownerDesignName>BORIS-HR</ownerDesignName>
</ColumnProxy>
<ColumnProxy name="ATTRIBUTE4" id="B4FB91AF-5DAB-2C4E-D3E5-783B89DEFDA4">
<createdBy>vs52761</createdBy>
<createdTime>2024-05-21 13:56:12 UTC</createdTime>
<ownerDesignName>BORIS-HR</ownerDesignName>
</ColumnProxy>
<ColumnProxy name="REQUEST_ID" id="B8D3CB24-C80A-45AD-B3C7-B666BAC29544">
<createdBy>vs52761</createdBy>
<createdTime>2024-05-21 13:56:12 UTC</createdTime>
<ownerDesignName>BORIS-HR</ownerDesignName>
</ColumnProxy>
<ColumnProxy name="LAST_UPDATE_LOGIN" id="BFFC2BF3-BB18-F542-C779-198EB32FAB8A">
<createdBy>vs52761</createdBy>
<createdTime>2024-05-21 13:56:12 UTC</createdTime>
<ownerDesignName>BORIS-HR</ownerDesignName>
</ColumnProxy>
<ColumnProxy name="ATTRIBUTE14" id="CC3E3E9A-E7A8-323E-1FB3-F70EAC8E9A38">
<createdBy>vs52761</createdBy>
<createdTime>2024-05-21 13:56:12 UTC</createdTime>
<ownerDesignName>BORIS-HR</ownerDesignName>
</ColumnProxy>
<ColumnProxy name="ATTRIBUTE11" id="D8007B72-8FF2-A78B-55A4-541892598C6E">
<createdBy>vs52761</createdBy>
<createdTime>2024-05-21 13:56:12 UTC</createdTime>
<ownerDesignName>BORIS-HR</ownerDesignName>
</ColumnProxy>
<ColumnProxy name="DATE_FROM" id="E3FE556C-D001-C026-F6A5-FB259563F253">
<createdBy>vs52761</createdBy>
<createdTime>2024-05-21 13:56:12 UTC</createdTime>
<ownerDesignName>BORIS-HR</ownerDesignName>
</ColumnProxy>
<ColumnProxy name="ATTRIBUTE18" id="E7B89FF5-56AB-7CDA-E4AD-4875C57A8EB1">
<createdBy>vs52761</createdBy>
<createdTime>2024-05-21 13:56:12 UTC</createdTime>
<ownerDesignName>BORIS-HR</ownerDesignName>
</ColumnProxy>
<ColumnProxy name="ATTRIBUTE9" id="EE1B554E-DC88-8288-EE16-371200158D47">
<createdBy>vs52761</createdBy>
<createdTime>2024-05-21 13:56:12 UTC</createdTime>
<ownerDesignName>BORIS-HR</ownerDesignName>
</ColumnProxy>
</columnProxies>
<indexProxies>
<IndexProxy class="oracle.dbtools.crest.model.design.storage.oracle.v10g.IndexProxyOraclev10g" name="PER_PERSON_ANALYSES_N3" id="14B2B036-F4AA-18E6-8775-F6E9BFB8B8D7">
<createdBy>vs52761</createdBy>
<createdTime>2024-05-21 13:56:20 UTC</createdTime>
<ownerDesignName>BORIS-HR</ownerDesignName>
<schemaObject>DF1B45F9-635F-5144-8353-0832859A4CDB</schemaObject>
<segment>E9BDBF29-B1EA-7596-F4D2-97B7F19102FF</segment>
<tableSpace>80D00F38-B1BB-76C4-4C5F-F32D8427BD07</tableSpace>
</IndexProxy>
<IndexProxy class="oracle.dbtools.crest.model.design.storage.oracle.v10g.IndexProxyOraclev10g" name="PER_PERSON_ANALYSES_N5" id="1F0B4071-FC4A-B48F-69C2-F7CBDC25516E">
<createdBy>vs52761</createdBy>
<createdTime>2024-05-21 13:56:20 UTC</createdTime>
<ownerDesignName>BORIS-HR</ownerDesignName>
<schemaObject>DF1B45F9-635F-5144-8353-0832859A4CDB</schemaObject>
<segment>6FB87BA9-BF40-092B-1065-6CC87B491819</segment>
<tableSpace>80D00F38-B1BB-76C4-4C5F-F32D8427BD07</tableSpace>
</IndexProxy>
<IndexProxy class="oracle.dbtools.crest.model.design.storage.oracle.v10g.IndexProxyOraclev10g" name="PER_PERSON_ANALYSES_FK1" id="78EB387C-779E-22D5-D320-ADE3008B5165">
<createdBy>vs52761</createdBy>
<createdTime>2024-05-21 13:56:20 UTC</createdTime>
<ownerDesignName>BORIS-HR</ownerDesignName>
<schemaObject>DF1B45F9-635F-5144-8353-0832859A4CDB</schemaObject>
<segment>E9BDBF29-B1EA-7596-F4D2-97B7F19102FF</segment>
<tableSpace>80D00F38-B1BB-76C4-4C5F-F32D8427BD07</tableSpace>
</IndexProxy>
<IndexProxy class="oracle.dbtools.crest.model.design.storage.oracle.v10g.IndexProxyOraclev10g" name="PER_PERSON_ANALYSES_PK" id="A48794B0-899C-DBD9-1A84-FBE2F406C6BE">
<createdBy>vs52761</createdBy>
<createdTime>2024-05-21 13:56:20 UTC</createdTime>
<ownerDesignName>BORIS-HR</ownerDesignName>
<schemaObject>DF1B45F9-635F-5144-8353-0832859A4CDB</schemaObject>
<segment>E9BDBF29-B1EA-7596-F4D2-97B7F19102FF</segment>
<tableSpace>80D00F38-B1BB-76C4-4C5F-F32D8427BD07</tableSpace>
</IndexProxy>
<IndexProxy class="oracle.dbtools.crest.model.design.storage.oracle.v10g.IndexProxyOraclev10g" name="PER_PERSON_ANALYSES_FK2" id="A91BA1AD-22AF-F894-5797-98C2CDDD2491">
<createdBy>vs52761</createdBy>
<createdTime>2024-05-21 13:56:20 UTC</createdTime>
<ownerDesignName>BORIS-HR</ownerDesignName>
<schemaObject>DF1B45F9-635F-5144-8353-0832859A4CDB</schemaObject>
<segment>E9BDBF29-B1EA-7596-F4D2-97B7F19102FF</segment>
<tableSpace>80D00F38-B1BB-76C4-4C5F-F32D8427BD07</tableSpace>
</IndexProxy>
</indexProxies>
<foreignKeys>
<ForeignKey class="oracle.dbtools.crest.model.design.storage.oracle.v10g.FKProxyOraclev10g" name="PER_PERSON_ANALYSES_FK2" id="397ACB0F-43BD-DB65-2BF0-B29B2403722F">
<createdBy>vs52761</createdBy>
<createdTime>2024-05-21 13:56:34 UTC</createdTime>
<ownerDesignName>BORIS-HR</ownerDesignName>
<validate>NO</validate>
</ForeignKey>
<ForeignKey class="oracle.dbtools.crest.model.design.storage.oracle.v10g.FKProxyOraclev10g" name="PER_PERSON_ANALYSES_FK1" id="455A5CFD-7825-2E43-F9BC-B41BBB0B9AD7">
<createdBy>vs52761</createdBy>
<createdTime>2024-05-21 13:56:34 UTC</createdTime>
<ownerDesignName>BORIS-HR</ownerDesignName>
<validate>NO</validate>
</ForeignKey>
</foreignKeys>
<lobStorages>
<LobStorage class="oracle.dbtools.crest.model.design.storage.oracle.v11g.LobStorageOraclev11g" name="SYS_LOB0000168458C00040$$" id="E7196962-ECAC-968F-EAB3-6AC874318B78">
<createdBy>vs52761</createdBy>
<createdTime>2024-05-21 13:56:35 UTC</createdTime>
<ownerDesignName>BORIS-HR</ownerDesignName>
<chunk>8192</chunk>
<column>COMMENTS</column>
<logging>YES</logging>
<tableSpace>A259311E-A01D-25F0-FFAD-F7D6D4B0EAC7</tableSpace>
</LobStorage>
</lobStorages>
<primaryKeys>
<PrimaryKey class="oracle.dbtools.crest.model.design.storage.oracle.v10g.PKProxyOraclev10g" name="PER_PERSON_ANALYSES_PK" id="8E3283D6-507D-E1A3-E1BF-B8C90F148CDE">
<createdBy>vs52761</createdBy>
<createdTime>2024-05-21 13:56:25 UTC</createdTime>
<ownerDesignName>BORIS-HR</ownerDesignName>
<segment>E9BDBF29-B1EA-7596-F4D2-97B7F19102FF</segment>
<tableSpace>80D00F38-B1BB-76C4-4C5F-F32D8427BD07</tableSpace>
<existingIndex>A48794B0-899C-DBD9-1A84-FBE2F406C6BE</existingIndex>
<indexSegment>E9BDBF29-B1EA-7596-F4D2-97B7F19102FF</indexSegment>
<indexSort>SORTED</indexSort>
<usingIndex>BY INDEX NAME</usingIndex>
</PrimaryKey>
</primaryKeys>
</TableProxyOraclev12c>